README.rst
setup.cfg
setup.py
smappi/__init__.py
smappi/exceptions.py
smappi/request.py
smappi.egg-info/PKG-INFO
smappi.egg-info/SOURCES.txt
smappi.egg-info/dependency_links.txt
smappi.egg-info/not-zip-safe
smappi.egg-info/top_level.txt