Metadata-Version: 1.1
Name: smappi
Version: 0.1.4
Summary: Python Client for Smappi API
Home-page: http://github.com/smappi/smappi-py
Author: Mikhail Andreev
Author-email: x11org@gmail.com
License: MIT
Keywords: smappi,api
Platform: UNKNOWN
Classifier: Development Status :: 3 - Alpha
Classifier: Environment :: Web Environment
Classifier: Programming Language :: Python
Classifier: License :: OSI Approved :: MIT License
Classifier: Topic :: Software Development :: Libraries :: Application Frameworks
Classifier: Topic :: Software Development :: Libraries :: Python Modules
